this_is_message_tel/__init__.py
this_is_message_tel-0.4.dist-info/METADATA
this_is_message_tel-0.4.dist-info/WHEEL
this_is_message_tel-0.4.dist-info/top_level.txt
this_is_message_tel-0.4.dist-info/RECORD
